MANIFEST.in
README.rst
requirements.txt
setup.py
cilium_microscope.egg-info/PKG-INFO
cilium_microscope.egg-info/SOURCES.txt
cilium_microscope.egg-info/dependency_links.txt
cilium_microscope.egg-info/entry_points.txt
cilium_microscope.egg-info/requires.txt
cilium_microscope.egg-info/top_level.txt
cilium_microscope.egg-info/zip-safe
microscope/__init__.py
microscope/__main__.py
microscope/batch/__init__.py
microscope/batch/batch.py
microscope/monitor/__init__.py
microscope/monitor/epresolver.py
microscope/monitor/monitor.py
microscope/monitor/parser.py
microscope/monitor/runner.py
microscope/monitor/test_monitor.py
microscope/ui/__init__.py
microscope/ui/ui.py