Metadata-Version: 1.2
Name: cilium-microscope
Version: 1.1.1
Summary: An urwid-based interface for watching `cilium monitor` events across your cluster
Home-page: https://github.com/cilium/microscope
Author: Maciej Kwiek
Author-email: maciej@covalent.io
License: Apache 2.0
Keywords: microscope,cilium,monitor,k8s,kubernetes
Platform: UNKNOWN
Classifier: Development Status :: 3 - Alpha
Classifier: Environment :: Console
Classifier: Intended Audience :: Developers
Classifier: Intended Audience :: System Administrators
Classifier: Natural Language :: English
Classifier: License :: OSI Approved :: Apache Software License
Classifier: Programming Language :: Python :: 3
Classifier: Programming Language :: Python :: 3.5
Classifier: Programming Language :: Python :: 3.6
Classifier: Programming Language :: Python :: Implementation :: CPython
Classifier: Topic :: System :: Systems Administration
Classifier: Topic :: System :: Networking :: Monitoring
Requires-Python: >=3.5
